mkepub/__init__.py
mkepub/mkepub.py
mkepub/templates/container.xml
mkepub/templates/cover.xhtml
mkepub/templates/package.opf
mkepub/templates/page.xhtml
mkepub/templates/toc.ncx
mkepub/templates/toc.xhtml
mkepub-1.2.2.dist-info/licenses/LICENSE
mkepub-1.2.2.dist-info/METADATA
mkepub-1.2.2.dist-info/WHEEL
mkepub-1.2.2.dist-info/top_level.txt
mkepub-1.2.2.dist-info/RECORD
