Metadata-Version: 2.4
Name: mkepub
Version: 1.2.2
Summary: Simple minimalistic library for creating EPUB3 files
Home-page: https://github.com/anqxyr/mkepub/
Author: anqxyr
Author-email: anqxyr <anqxyr@gmail.com>
License-Expression: MIT
Project-URL: Homepage, https://github.com/anqxyr/mkepub
Keywords: epub,books
Classifier: Development Status :: 5 - Production/Stable
Classifier: Intended Audience :: Developers
Classifier: Operating System :: OS Independent
Classifier: Programming Language :: Python
Requires-Python: >=3.10
License-File: LICENSE
Requires-Dist: jinja2>=3.1.6
Requires-Dist: puremagic>=1.30
Dynamic: author
Dynamic: home-page
Dynamic: license-file
Dynamic: requires-python
